thermodynamics/__init__.py
thermodynamics/helpers/__init__.py
thermodynamics/helpers/alfaFunctions.py
thermodynamics/helpers/eos.py
thermodynamics/helpers/eosHelpers.py
thermodynamics/helpers/mixing_rules.py
thermodynamics/helpers/temperatureCorrelations.py
thermodynamics/mix/__init__.py
thermodynamics/mix/binaryDiagrams.py
thermodynamics/mix/diagrams.py
thermodynamics/mix/equilibrium.py
thermodynamics/pure/__init__.py
thermodynamics/pure/diagrams.py
thermodynamics/pure/equilibrium.py
thermodynamics/solvers/__init__.py
thermodynamics/solvers/cubicSolver.py
thermodynamics-0.0.85.dist-info/LICENSE
thermodynamics-0.0.85.dist-info/METADATA
thermodynamics-0.0.85.dist-info/WHEEL
thermodynamics-0.0.85.dist-info/top_level.txt
thermodynamics-0.0.85.dist-info/RECORD
